neurora/__init__.py
neurora/corr_cal.py
neurora/corr_cal_by_rdm.py
neurora/ctcorr_cal.py
neurora/ctrdm_cal.py
neurora/ctrdm_corr.py
neurora/decoding.py
neurora/isc_cal.py
neurora/nii_save.py
neurora/nps_cal.py
neurora/rdm_cal.py
neurora/rdm_corr.py
neurora/rsa_plot.py
neurora/stats_cal.py
neurora/stps_cal.py
neurora/stuff.py
neurora/template/HarvardOxford-cort-maxprob-thr0-1mm.nii.gz
neurora/template/ch2.nii.gz
neurora/template/ch2bet.nii.gz
neurora-1.1.6.12.dist-info/LICENSE
neurora-1.1.6.12.dist-info/METADATA
neurora-1.1.6.12.dist-info/WHEEL
neurora-1.1.6.12.dist-info/top_level.txt
neurora-1.1.6.12.dist-info/RECORD
