Metadata-Version: 2.1
Name: neurora
Version: 1.1.6.12
Summary: A Python Toolbox for Multimodal Neural Data Representation Analysis
Home-page: https://github.com/ZitongLu1996/NeuroRA
Author: Zitong Lu
Author-email: zitonglu1996@gmail.com
Maintainer: Zitong Lu
Maintainer-email: zitonglu1996@gmail.com
License: MIT License
Platform: all
Classifier: Development Status :: 4 - Beta
Classifier: Operating System :: OS Independent
Classifier: Intended Audience :: Developers
Classifier: License :: OSI Approved :: BSD License
Classifier: Programming Language :: Python
Classifier: Programming Language :: Python :: Implementation
Classifier: Programming Language :: Python :: 3
Classifier: Topic :: Software Development :: Libraries
License-File: LICENSE
Requires-Dist: numpy
Requires-Dist: scipy (>=1.6.2)
Requires-Dist: mne
Requires-Dist: nibabel
Requires-Dist: matplotlib
Requires-Dist: nilearn
Requires-Dist: scikit-learn
Requires-Dist: scikit-image
